Workbook

Sheet Salary_Sheet
A1: আশা ও আলো সমাজকল্যাণ সংস্থা (Asha & Alo Development Society)
A2: প্রজেক্ট: সমন্বিত পল্লী উন্নয়ন ও সামাজিক ক্ষমতায়ন কর্মসূচি (ICDP) | ডোনার: PKSF / Global Fund
A3: কর্মকর্তা ও কর্মচারীদের মাসিক বেতন ও ভাতা বিবরণী (Salary & Allowance Sheet) - অক্টোবর ২০২৬
A5: সাধারণ তথ্য (General Info) | G5: বেতন ও ভাতা (Earnings & Allowances) | M5: হাজিরা ও LWP (Attendance) | P5: কর্তনসমূহ (Monthly Deductions) | T5: চূড়ান্ত প্রদেয় (Final Settlement)
A6: ক্রমিক (SL) | B6: আইডি (Emp ID) | C6: কর্মচারীর নাম (Employee Name) | D6: পদবী (Designation) | E6: প্রজেক্ট কোড (Project Code) | F6: ব্যাংক একাউন্ট নং (Bank A/C No) | G6: মূল বেতন (Basic Salary) | H6: বাড়ি ভাড়া (House Rent (50%)) | I6: চিকিৎসা (Medical Allow.) | J6: যাতায়াত (Conveyance) | K6: মোবাইল/অন্যান্য (Mobile/Other) | L6: মোট গ্রস বেতন (Gross Salary) | M6: মোট দিন (Total Days) | N6: বিনা বেতনে ছুটি (LWP Days) | O6: LWP কর্তন (LWP Deduct) | P6: প্রভিডেন্ট ফান্ড (PF (10% Basic)) | Q6: আয়কর (TDS) (Income Tax) | R6: লোন/অগ্রিম (Loan/Advance) | S6: মোট কর্তন (Total Deduct) | T6: নিট প্রদেয় বেতন (Net Payable) | U6: প্রাপকের স্বাক্ষর / নোট (Signature)
A7: 1 | B7: AA-101 | C7: মোহাম্মদ রফিকুল ইসলাম | D7: প্রজেক্ট ম্যানেজার (PM) | E7: ICDP-01 | F7: 102345678901 | G7: 45000 | H7: =ROUND(G7*0.5, 0) | I7: 2000 | J7: 3000 | K7: 1500 | L7: =SUM(G7:K7) | M7: 31 | N7: 0 | O7: =ROUND((L7/M7)*N7, 0) | P7: =ROUND(G7*0.1, 0) | Q7: 1200 | R7: 0 | S7: =SUM(O7:R7) | T7: =L7-S7 | U7: Account Transfer
A8: 2 | B8: AA-102 | C8: ফারহানা আক্তার | D8: সিনিয়র হিসাব রক্ষক (Sr. Accountant) | E8: ICDP-01 | F8: 102345678902 | G8: 32000 | H8: =ROUND(G8*0.5, 0) | I8: 1800 | J8: 2000 | K8: 1000 | L8: =SUM(G8:K8) | M8: 31 | N8: 0 | O8: =ROUND((L8/M8)*N8, 0) | P8: =ROUND(G8*0.1, 0) | Q8: 500 | R8: 0 | S8: =SUM(O8:R8) | T8: =L8-S8 | U8: Account Transfer
A9: 3 | B9: AA-103 | C9: তানভীর আহমেদ | D9: মনিটরিং অফিসার (M&E) | E9: ICDP-02 | F9: 102345678903 | G9: 28000 | H9: =ROUND(G9*0.5, 0) | I9: 1500 | J9: 2500 | K9: 1000 | L9: =SUM(G9:K9) | M9: 31 | N9: 1 | O9: =ROUND((L9/M9)*N9, 0) | P9: =ROUND(G9*0.1, 0) | Q9: 0 | R9: 2000 | S9: =SUM(O9:R9) | T9: =L9-S9 | U9: Account Transfer
A10: 4 | B10: AA-104 | C10: নাসরিন সুলতানা | D10: হিসাব সহকারী (Accounts Assistant) | E10: ICDP-01 | F10: 102345678904 | G10: 22000 | H10: =ROUND(G10*0.5, 0) | I10: 1500 | J10: 1500 | K10: 800 | L10: =SUM(G10:K10) | M10: 31 | N10: 0 | O10: =ROUND((L10/M10)*N10, 0) | P10: =ROUND(G10*0.1, 0) | Q10: 0 | R10: 0 | S10: =SUM(O10:R10) | T10: =L10-S10 | U10: Account Transfer
A11: 5 | B11: AA-105 | C11: কামরুল হাসান | D11: ফিল্ড কো-অর্ডিনেটর | E11: ICDP-02 | F11: 102345678905 | G11: 25000 | H11: =ROUND(G11*0.5, 0) | I11: 1500 | J11: 3000 | K11: 800 | L11: =SUM(G11:K11) | M11: 31 | N11: 2 | O11: =ROUND((L11/M11)*N11, 0) | P11: =ROUND(G11*0.1, 0) | Q11: 0 | R11: 1500 | S11: =SUM(O11:R11) | T11: =L11-S11 | U11: Account Transfer
A12: 6 | B12: AA-106 | C12: সুলতানা রাজিয়া | D12: কমিউনিটি অর্গানাইজার (CO) | E12: ICDP-02 | F12: 102345678906 | G12: 18000 | H12: =ROUND(G12*0.5, 0) | I12: 1200 | J12: 1500 | K12: 500 | L12: =SUM(G12:K12) | M12: 31 | N12: 0 | O12: =ROUND((L12/M12)*N12, 0) | P12: =ROUND(G12*0.1, 0) | Q12: 0 | R12: 0 | S12: =SUM(O12:R12) | T12: =L12-S12 | U12: Account Transfer
A13: 7 | B13: AA-107 | C13: আব্দুল কাদের | D13: মাঠ কর্মকর্তা (Credit Officer) | E13: ICDP-03 | F13: 102345678907 | G13: 19000 | H13: =ROUND(G13*0.5, 0) | I13: 1200 | J13: 2000 | K13: 500 | L13: =SUM(G13:K13) | M13: 31 | N13: 0 | O13: =ROUND((L13/M13)*N13, 0) | P13: =ROUND(G13*0.1, 0) | Q13: 0 | R13: 1000 | S13: =SUM(O13:R13) | T13: =L13-S13 | U13: Account Transfer
A14: 8 | B14: AA-108 | C14: সোহেল রানা | D14: অফিস সহকারী ও সাপোর্ট স্টাফ | E14: ICDP-01 | F14: 102345678908 | G14: 14000 | H14: =ROUND(G14*0.5, 0) | I14: 1000 | J14: 1000 | K14: 300 | L14: =SUM(G14:K14) | M14: 31 | N14: 0 | O14: =ROUND((L14/M14)*N14, 0) | P14: =ROUND(G14*0.1, 0) | Q14: 0 | R14: 0 | S14: =SUM(O14:R14) | T14: =L14-S14 | U14: Account Transfer
A15: সর্বমোট (Grand Total): | G15: =SUM(G7:G14) | H15: =SUM(H7:H14) | I15: =SUM(I7:I14) | J15: =SUM(J7:J14) | K15: =SUM(K7:K14) | L15: =SUM(L7:L14) | O15: =SUM(O7:O14) | P15: =SUM(P7:P14) | Q15: =SUM(Q7:Q14) | R15: =SUM(R7:R14) | S15: =SUM(S7:S14) | T15: =SUM(T7:T14)
B19: ---------------------------------- | H19: ---------------------------------- | N19: ---------------------------------- | T19: ----------------------------------
B20: প্রস্তুতকারী (Prepared By) হিসাব রক্ষক (Accounts Officer) | H20: নিরীক্ষাকারী (Checked By) ইন্টারনাল অডিটর (Auditor) | N20: যাচাইকারী (Verified By) প্রজেক্ট ম্যানেজার (Project Manager) | T20: অনুমোদনকারী (Approved By) নির্বাহী পরিচালক (Executive Director)

Sheet Bank_Advice_Letter
A1: আশা ও আলো সমাজকল্যাণ সংস্থা
A2: প্রধান কার্যালয়, বাড়ি # ১২, রোড # ৪, ধানমন্ডি, ঢাকা-১২০৫
A4: তারিখ: ৩১ অক্টোবর ২০২৬
A6: বরাবর,
A7: শাখা ব্যবস্থাপক (Branch Manager)
A8: ডাচ-বাংলা ব্যাংক পিএলসি (Dutch-Bangla Bank PLC)
A9: ধানমন্ডি শাখা, ঢাকা।
A11: বিষয়: অক্টোবর ২০২৬ মাসের কর্মকর্তা ও কর্মচারীদের বেতন ব্যাংক অ্যাকাউন্টে স্থানান্তর প্রসঙ্গে।
A13: জনাব,
A14: সবিনয় নিবেদন এই যে, আমাদের সংস্থার 'সমন্বিত পল্লী উন্নয়ন কর্মসূচি (ICDP)'-এর চলতি হিসাব নং: 1021200045678 থেকে সংযুক্ত তালিকা অনুযায়ী কর্মকর্তা-কর্মচারীদের ব্যক্তিগত ব্যাংক অ্যাকাউন্টে তাদের নামের পার্শ্বে বর্ণিত নিট বেতনের টাকা স্থানান্তর (Fund Transfer) করার জন্য অনুরোধ জানাচ্ছি।
A15: মোট বেতনের পরিমাণ: =Salary_Sheet!T15 টাকা (কথায়: ব্যাংক হিসাব বিবরণী অনুযায়ী)।
A17: ক্রমিক | B17: কর্মচারীর নাম | C17: পদবী | D17: ব্যাংক একাউন্ট নম্বর | E17: প্রদেয় নিট বেতন (টাকা)
A18: 1 | B18: =Salary_Sheet!C7 | C18: =Salary_Sheet!D7 | D18: =Salary_Sheet!F7 | E18: =Salary_Sheet!T7
A19: 2 | B19: =Salary_Sheet!C8 | C19: =Salary_Sheet!D8 | D19: =Salary_Sheet!F8 | E19: =Salary_Sheet!T8
A20: 3 | B20: =Salary_Sheet!C9 | C20: =Salary_Sheet!D9 | D20: =Salary_Sheet!F9 | E20: =Salary_Sheet!T9
A21: 4 | B21: =Salary_Sheet!C10 | C21: =Salary_Sheet!D10 | D21: =Salary_Sheet!F10 | E21: =Salary_Sheet!T10
A22: 5 | B22: =Salary_Sheet!C11 | C22: =Salary_Sheet!D11 | D22: =Salary_Sheet!F11 | E22: =Salary_Sheet!T11
A23: 6 | B23: =Salary_Sheet!C12 | C23: =Salary_Sheet!D12 | D23: =Salary_Sheet!F12 | E23: =Salary_Sheet!T12
A24: 7 | B24: =Salary_Sheet!C13 | C24: =Salary_Sheet!D13 | D24: =Salary_Sheet!F13 | E24: =Salary_Sheet!T13
A25: 8 | B25: =Salary_Sheet!C14 | C25: =Salary_Sheet!D14 | D25: =Salary_Sheet!F14 | E25: =Salary_Sheet!T14
A26: সর্বমোট স্থানান্তর: | E26: =SUM(E18:E25)
A30: ধন্যবাদান্তে,
A33: ------------------------------- (স্বাক্ষর ও সিল) প্রধান হিসাব কর্মকর্তা | D33: ------------------------------- (স্বাক্ষর ও সিল) নির্বাহী পরিচালক

Sheet Individual_Pay_Slip
A1: আশা ও আলো সমাজকল্যাণ সংস্থা
A2: মাসিক বেতন বিবরণী (Pay Slip) - অক্টোবর ২০২৬
A4: স্টাফ আইডি: | B4: =Salary_Sheet!B7 | D4: প্রজেক্ট কোড: | E4: =Salary_Sheet!E7
A5: কর্মচারীর নাম: | B5: =Salary_Sheet!C7 | D5: ব্যাংক একাউন্ট: | E5: =Salary_Sheet!F7
A6: পদবী: | B6: =Salary_Sheet!D7 | D6: মোট উপস্থিত দিন: | E6: =Salary_Sheet!M7 - Salary_Sheet!N7
A8: উপার্জনসমূহ (Earnings) | D8: কর্তনসমূহ (Deductions)
A9: মূল বেতন (Basic Salary) | C9: =Salary_Sheet!G7 | D9: প্রভিডেন্ট ফান্ড (PF 10%) | F9: =Salary_Sheet!P7
A10: বাড়ি ভাড়া ভাতা (House Rent 50%) | C10: =Salary_Sheet!H7 | D10: উৎস আয়কর (TDS / Income Tax) | F10: =Salary_Sheet!Q7
A11: চিকিৎসা ভাতা (Medical Allowance) | C11: =Salary_Sheet!I7 | D11: স্টাফ লোন / অগ্রিম কর্তন | F11: =Salary_Sheet!R7
A12: যাতায়াত ভাতা (Conveyance) | C12: =Salary_Sheet!J7 | D12: বিনা বেতনে ছুটি কর্তন (LWP) | F12: =Salary_Sheet!O7
A13: মোবাইল ও অন্যান্য ভাতা | C13: =Salary_Sheet!K7 | D13: অন্যান্য কর্তন | F13: 0
A14: মোট উপার্জন (Gross Earnings): | C14: =SUM(C9:C13) | D14: মোট কর্তন (Total Deductions): | F14: =SUM(F9:F13)
A16: নিট প্রদেয় বেতন (Net Payable Amount): | E16: =C14-F14
A19: -------------------------------------- কর্মচারীর স্বাক্ষর | E19: -------------------------------------- হিসাব কর্মকর্তার স্বাক্ষর

Sheet User_Guide_নির্দেশিকা
A1: এনজিও স্যালারি শিট টেমপ্লেট ব্যবহার বিধি ও ফর্মুলা গাইড
A3: ১. এই এক্সেল ফাইলে ব্যবহৃত স্বয়ংক্রিয় ফর্মুলাসমূহ:
A4: • বাড়ি ভাড়া (House Rent): =ROUND(G7*0.5, 0) -> মূল বেতনের ৫০% স্বয়ংক্রিয়ভাবে হিসাব হবে।
A5: • মোট গ্রস বেতন (Gross Salary): =SUM(G7:K7) -> Basic থেকে অন্যান্য ভাতার যোগফল।
A6: • বিনা বেতনে ছুটি কর্তন (LWP): =ROUND((L7/M7)*N7, 0) -> (গ্রস বেতন ÷ মোট দিন) × ছুটির দিন।
A7: • প্রভিডেন্ট ফান্ড (PF): =ROUND(G7*0.1, 0) -> মূল বেতনের ১০% কর্তন।
A8: • মোট কর্তন (Total Deductions): =SUM(O7:R7) -> সকল কর্তনের যোগফল।
A9: • নিট প্রদেয় বেতন (Net Payable): =L7-S7 -> মোট গ্রস বেতন থেকে মোট কর্তন বাদ।
A11: ২. নতুন কর্মচারী যুক্ত করার নিয়ম:
A12: • ৮ নম্বর কর্মচারীর নিচের সারিতে নতুন সারি (Row) ইনসার্ট করুন।
A13: • উপরের সারির ফর্মুলাগুলো (কলাম H, L, O, P, S, T) নতুন সারিতে টেনে ড্র্যাগ (Copy/Drag) করে নামিয়ে দিন।
A14: • Grand Total স্বয়ংক্রিয়ভাবে নতুন কর্মচারীর বেতন সহ আপডেট হয়ে যাবে।
... A18: • 'Individual_Pay_Slip' শিটটি কোনো নির্দিষ্ট কর্মীর পে-স্লিপ প্রিন্ট করার জন্য ব্যবহার করতে পারেন।
